pg_batch/__init__.py
pg_batch/__main__.py
pg_batch/pg_batch.py
pg_batch-1.1.1.dist-info/LICENSE
pg_batch-1.1.1.dist-info/METADATA
pg_batch-1.1.1.dist-info/WHEEL
pg_batch-1.1.1.dist-info/entry_points.txt
pg_batch-1.1.1.dist-info/top_level.txt
pg_batch-1.1.1.dist-info/RECORD
