Metadata-Version: 2.1
Name: pg-batch
Version: 1.1.1
Summary: Run large PostgreSQL UPDATE and DELETE queries with small batches to prevent locks
Home-page: https://github.com/gabfl/pg-batch
Author: Gabriel Bordeaux
Author-email: pypi@gab.lc
License: MIT
Platform: UNKNOWN
Classifier: Topic :: Software Development
Classifier: Topic :: Database
Classifier: Topic :: Database :: Database Engines/Servers
Classifier: License :: OSI Approved :: MIT License
Classifier: Operating System :: MacOS
Classifier: Operating System :: POSIX :: Linux
Classifier: Natural Language :: English
Classifier: Programming Language :: Python :: 2.7
Classifier: Programming Language :: Python :: 3
Classifier: Programming Language :: Python
Classifier: Development Status :: 5 - Production/Stable
License-File: LICENSE
Requires-Dist: psycopg2-binary (==2.9.*)
